akkpredict/__init__.py
akkpredict/moonapi.py
akkpredict/test.py
akkpredict-0.0.1.dist-info/LICENSE
akkpredict-0.0.1.dist-info/METADATA
akkpredict-0.0.1.dist-info/WHEEL
akkpredict-0.0.1.dist-info/top_level.txt
akkpredict-0.0.1.dist-info/RECORD
