Metadata-Version: 2.1
Name: akkpredict
Version: 0.0.1
Summary: A package for predicting buy and sell signals
Home-page: https://nkrtech.com
Download-URL: https://github.com/moinonin/akkpredict/archive/refs/heads/main.zip
Author: Nicolus Rotich
Author-email: nicholas.rotich@gmail.com
License: MIT
Project-URL: Bug Tracker, https://github.com/pypa/akkpredict/issues
Platform: any
Classifier: License :: OSI Approved :: MIT License
Requires-Python: >=3.8
License-File: LICENSE
Requires-Dist: setuptools (>=58.1.0)
Requires-Dist: aiohttp (>=3.8.1)
Requires-Dist: requests (>=2.27.1)
Requires-Dist: fire
